README.rst
setup.py
kite/__init__.py
kite/cli.py
kite/help_messages.py
kite/takosan.py
kite/version.py
kite_string.egg-info/PKG-INFO
kite_string.egg-info/SOURCES.txt
kite_string.egg-info/dependency_links.txt
kite_string.egg-info/entry_points.txt
kite_string.egg-info/requires.txt
kite_string.egg-info/top_level.txt