Metadata-Version: 1.1
Name: kite-string
Version: 0.0.0.dev5
Summary: command-line HTTP request wrapper for takosan .
Home-page: https://github.com/laughk/kite-string
Author: Kei Iwasaki
Author-email: me@laughk.org
License: MIT License
Platform: UNKNOWN
Classifier: License :: OSI Approved :: MIT License
Classifier: Programming Language :: Python :: 2.6
Classifier: Programming Language :: Python :: 2.7
Classifier: Programming Language :: Python :: 3
